lab_device_sdk/__init__.py
lab_device_sdk/device.py
lab_device_sdk/py.typed
lab_device_sdk-0.1.3.dist-info/METADATA
lab_device_sdk-0.1.3.dist-info/WHEEL
lab_device_sdk-0.1.3.dist-info/top_level.txt
lab_device_sdk-0.1.3.dist-info/RECORD
