Metadata-Version: 2.4
Name: lab-device-sdk
Version: 0.1.3
Summary: Library for classes and functions that are used for the development of device managers.
Author: Eli Fine
Classifier: Programming Language :: Python :: 3
Classifier: Programming Language :: Python :: 3.12
Requires-Python: >=3.12.7
